miniqt/MiniqtDataBase.db
miniqt/MiniqtDataBase.db-shm
miniqt/MiniqtDataBase.db-wal
miniqt/MiniqtDataBase.py
miniqt/__init__.py
miniqt/cli.py
miniqt/fluent.py
miniqt/settings.ini
miniqt/utils.py
miniqt/__pycache__/MiniqtDataBase.cpython-39.pyc
miniqt/__pycache__/__init__.cpython-39.pyc
miniqt/__pycache__/cli.cpython-39.pyc
miniqt/__pycache__/fluent.cpython-39.pyc
miniqt/__pycache__/utils.cpython-39.pyc
miniqt/app/gallery.pro
miniqt/app/common/config.py
miniqt/app/common/icon.py
miniqt/app/common/resource.py
miniqt/app/common/signal_bus.py
miniqt/app/common/style_sheet.py
miniqt/app/common/translator.py
miniqt/app/common/trie.py
miniqt/app/components/link_card.py
miniqt/app/components/sample_card.py
miniqt/app/config/config.json
miniqt/app/login/LoginWindow.py
miniqt/app/login/Ui_LoginWindow.py
miniqt/app/login/background.jpg
miniqt/app/login/logo.png
miniqt/app/login/pytdx_api.py
miniqt/app/login/resource_rc.py
miniqt/app/login/settings.ini
miniqt/app/login/tq_api.py
miniqt/app/resource/resource.qrc
miniqt/app/resource/i18n/gallery.zh_CN.qm
miniqt/app/resource/i18n/gallery.zh_CN.ts
miniqt/app/resource/i18n/gallery.zh_HK.qm
miniqt/app/resource/i18n/gallery.zh_HK.ts
miniqt/app/resource/images/Dvd.png
miniqt/app/resource/images/Gyro.jpg
miniqt/app/resource/images/MusicNote.png
miniqt/app/resource/images/SBR.jpg
miniqt/app/resource/images/Shoko1.jpg
miniqt/app/resource/images/Shoko2.jpg
miniqt/app/resource/images/Shoko3.jpg
miniqt/app/resource/images/Shoko4.jpg
miniqt/app/resource/images/Singer.png
miniqt/app/resource/images/Smiling_with_heart.png
miniqt/app/resource/images/chidanta.jpg
miniqt/app/resource/images/chidanta2.jpg
miniqt/app/resource/images/chidanta3.jpg
miniqt/app/resource/images/chidanta4.jpg
miniqt/app/resource/images/chidanta5.jpg
miniqt/app/resource/images/header.png
miniqt/app/resource/images/header1.png
miniqt/app/resource/images/kunkun.png
miniqt/app/resource/images/logo.png
miniqt/app/resource/images/shoko.png
miniqt-0.1.0.dist-info/licenses/LICENSE
miniqt-0.1.0.dist-info/METADATA
miniqt-0.1.0.dist-info/WHEEL
miniqt-0.1.0.dist-info/entry_points.txt
miniqt-0.1.0.dist-info/top_level.txt
miniqt-0.1.0.dist-info/RECORD
