Metadata-Version: 2.4
Name: miniqt
Version: 0.1.0
Summary: 一站式量化交易策略开发库，简化从策略搭建到实盘交易的全流程
Author-email: owen <407841129@qq.com>
License: MIT
Project-URL: Homepage, https://github.com/MiniBtMaster/miniqt
Classifier: Programming Language :: Python :: 3
Classifier: Programming Language :: Python :: 3.8
Classifier: Programming Language :: Python :: 3.9
Classifier: Programming Language :: Python :: 3.10
Classifier: Operating System :: OS Independent
Classifier: Intended Audience :: Developers
Classifier: Intended Audience :: Financial and Insurance Industry
Classifier: Topic :: Software Development :: Libraries :: Python Modules
Classifier: Topic :: Office/Business :: Financial :: Investment
Requires-Python: >=3.8
License-File: LICENSE
Requires-Dist: click
Requires-Dist: minibt
Dynamic: license-file
